gymfolio/envs/__init__.py
gymfolio/envs/base.py
gymfolio/envs/common.py
gymfolio/envs/custom.py
gymfolio/envs/metrics.py
gymfolio/envs/UML_envs.png
gymfolio-0.2.1.dist-info/LICENSE.txt
gymfolio-0.2.1.dist-info/METADATA
gymfolio-0.2.1.dist-info/WHEEL
gymfolio-0.2.1.dist-info/RECORD
