Metadata-Version: 2.3
Name: gymfolio
Version: 0.2.1
Summary: Reinforcement Learning environment for Portfolio Optimization
License: GPL-3.0-only
Author: franespiga
Author-email: francisco.espiga.fernandez@gmail.com
Requires-Python: >=3.12,<4.0
Classifier: License :: OSI Approved :: GNU General Public License v3 (GPLv3)
Classifier: Programming Language :: Python :: 3
Classifier: Programming Language :: Python :: 3.12
Classifier: Programming Language :: Python :: 3.13
Requires-Dist: gymnasium (>=1.1,<2.0)
Requires-Dist: numpy (>=2.2,<3.0)
Requires-Dist: pandas (>=2.2.2,<3.0.0)
Requires-Dist: stable-baselines3 (>=2.3.2,<3.0.0)
Requires-Dist: tables (>=3.8.0,<4.0.0)
Requires-Dist: torch (>=2.4,<3.0)
Requires-Dist: tqdm (>=4.66.1,<5.0.0)
Project-URL: Documentation, https://franespiga.github.io/gymfolio/overview.html
Project-URL: Homepage, https://franespiga.github.io/gymfolio/
Project-URL: Repository, https://github.com/franespiga/gymfolio
